[
  {
    "model": "dogs.breed",
    "pk": 1,
    "fields": {
      "name": "Немецкая овчарка",
      "description": "Хороший сторож. Большая и пушистая!"
    }
  },
  {
    "model": "dogs.breed",
    "pk": 2,
    "fields": {
      "name": "Колли",
      "description": "Снималась в кино"
    }
  },
  {
    "model": "dogs.breed",
    "pk": 3,
    "fields": {
      "name": "Джек Рассел Терьер",
      "description": "Активная порода известна по фильму макска"
    }
  },
  {
    "model": "dogs.breed",
    "pk": 4,
    "fields": {
      "name": "Чихуахуа",
      "description": "Зло во плоти"
    }
  },
  {
    "model": "dogs.dog",
    "pk": 2,
    "fields": {
      "name": "Джессика",
      "breed": 4,
      "photo": "dogs/images_3hFTTKX.jpeg",
      "birth_date": "2018-08-04T19:00:00Z",
      "owner": 3
    }
  }
]