[
  {
    "model": "dogs.breed",
    "pk": 1,
    "fields": {
      "name": "Немецкая овчарка",
      "description": "Хороший сторож. Большая и пушистая!"
    }
  },
  {
    "model": "dogs.breed",
    "pk": 2,
    "fields": {
      "name": "Колли",
      "description": "Снималась в кино"
    }
  },
  {
    "model": "dogs.breed",
    "pk": 3,
    "fields": {
      "name": "Джек Рассел Терьер",
      "description": "Активная порода известна по фильму макска"
    }
  },
  {
    "model": "dogs.breed",
    "pk": 4,
    "fields": {
      "name": "Чихуахуа",
      "description": "Зло во плоти"
    }
  },
  {
    "model": "dogs.dog",
    "pk": 2,
    "fields": {
      "name": "Джессика",
      "breed": 4,
      "photo": "dogs/images_3hFTTKX.jpeg",
      "birth_date": "2018-08-04",
      "is_active": true,
      "owner": 3,
      "views": 4
    }
  },
  {
    "model": "dogs.dog",
    "pk": 3,
    "fields": {
      "name": "Афган",
      "breed": 1,
      "photo": "dogs/загрузка_4j7OmyB.jpeg",
      "birth_date": "2018-08-05",
      "is_active": true,
      "owner": 4,
      "views": 0
    }
  },
  {
    "model": "dogs.dog",
    "pk": 4,
    "fields": {
      "name": "Джек",
      "breed": 2,
      "photo": "dogs/загрузка_bMrbtBL.jpeg",
      "birth_date": "2018-08-05",
      "is_active": false,
      "owner": 4,
      "views": 0
    }
  }
]